metroloj/__init__.py
metroloj/common.py
metroloj/cv.py
metroloj/homo.py
metroloj/metadata.py
metroloj-0.1.2.data/scripts/metroloj_script
metroloj-0.1.2.dist-info/METADATA
metroloj-0.1.2.dist-info/WHEEL
metroloj-0.1.2.dist-info/top_level.txt
metroloj-0.1.2.dist-info/RECORD
