Metadata-Version: 2.1
Name: metroloj
Version: 0.1.2
Summary: A python implementation of ImageJ MetroloJ plugin
Home-page: https://github.com/javatechy/dokr
Author: Youssef Ayachi
Author-email: youssef-ayachi@outlook.com
License: UNKNOWN
Platform: UNKNOWN
Classifier: Programming Language :: Python :: 3
Classifier: License :: OSI Approved :: MIT License
Classifier: Operating System :: OS Independent
